bng_latlon/__init__.py
bng_latlon/bng_to_latlon.py
bng_latlon/latlon_to_bng.py
bng_latlon-1.0.3.dist-info/LICENSE
bng_latlon-1.0.3.dist-info/METADATA
bng_latlon-1.0.3.dist-info/WHEEL
bng_latlon-1.0.3.dist-info/top_level.txt
bng_latlon-1.0.3.dist-info/RECORD
