Metadata-Version: 2.1
Name: bng-latlon
Version: 1.0.3
Summary: Converts british national grid (OSBG36) to lat lon (WGS84) and vice versa.
Home-page: https://github.com/fmalina/blocl-bnglatlon
Author: Hannah Fry, F. Malina
Author-email: hi@blocl.com
License: MIT License
Project-URL: Homepage, https://blocl.uk
Project-URL: Funding, https://unilexicon.com/fm/pay.html
Project-URL: Source, https://github.com/fmalina/blocl-bnglatlon
Keywords: GPS,OSGB
Platform: UNKNOWN
Classifier: Development Status :: 5 - Production/Stable
Classifier: Programming Language :: Python :: 2.7
Classifier: Programming Language :: Python :: 3
Classifier: Intended Audience :: Developers
Classifier: Intended Audience :: Science/Research
Classifier: Intended Audience :: Information Technology
Classifier: License :: OSI Approved :: MIT License
Classifier: Topic :: Scientific/Engineering :: GIS
License-File: LICENSE
